MANIFEST.in
README.md
setup.py
admitad/__init__.py
admitad/abstract_models.py
admitad/admin.py
admitad/apps.py
admitad/gateway.py
admitad/models.py
admitad/utils.py
admitad/migrations/0001_initial.py
admitad/migrations/0002_auto_20181127_1329.py
admitad/migrations/0003_auto_20181127_1417.py
admitad/migrations/__init__.py
django_admitad.egg-info/PKG-INFO
django_admitad.egg-info/SOURCES.txt
django_admitad.egg-info/dependency_links.txt
django_admitad.egg-info/requires.txt
django_admitad.egg-info/top_level.txt